mineterm/__init__.py
mineterm/__main__.py
mineterm/css/mineterm.css
mineterm/game.py
mineterm/mineterm.py
mineterm/ui.py
mineterm/utils.py
mineterm-0.0.0.dist-info/LICENSE
mineterm-0.0.0.dist-info/METADATA
mineterm-0.0.0.dist-info/WHEEL
mineterm-0.0.0.dist-info/RECORD
