Metadata-Version: 2.1
Name: mineterm
Version: 0.0.0
Summary: A simple Minecraft launcher for the terminal.
License: MIT
Author: mudkipdev
Author-email: mudkip@mudkip.dev
Requires-Python: >=3.11,<4.0
Classifier: License :: OSI Approved :: MIT License
Classifier: Programming Language :: Python :: 3
Classifier: Programming Language :: Python :: 3.11
Requires-Dist: textual (>=0.23.0,<0.24.0)
